LICENSE
MANIFEST.in
README
README.md
requirements-dev.txt
requirements.txt
runtests
setup.py
bin/grouper-api
bin/grouper-fe
bin/shell
bin/sync_db
bin/user_proxy
grouper/__init__.py
grouper/capabilities.py
grouper/constants.py
grouper/exc.py
grouper/graph.py
grouper/models.py
grouper/settings.py
grouper/util.py
grouper/version.py
grouper.egg-info/PKG-INFO
grouper.egg-info/SOURCES.txt
grouper.egg-info/dependency_links.txt
grouper.egg-info/requires.txt
grouper.egg-info/top_level.txt
grouper/api/__init__.py
grouper/api/handlers.py
grouper/api/routes.py
grouper/api/settings.py
grouper/fe/__init__.py
grouper/fe/forms.py
grouper/fe/handlers.py
grouper/fe/routes.py
grouper/fe/settings.py
grouper/fe/util.py
grouper/fe/static/favicon.ico
grouper/fe/static/css/grouper.css
grouper/fe/static/js/grouper.js
grouper/fe/templates/base.html
grouper/fe/templates/group-create.html
grouper/fe/templates/group-edit.html
grouper/fe/templates/group-join.html
grouper/fe/templates/group-request-update.html
grouper/fe/templates/group-requests.html
grouper/fe/templates/group.html
grouper/fe/templates/groups.html
grouper/fe/templates/help.html
grouper/fe/templates/index.html
grouper/fe/templates/search.html
grouper/fe/templates/user.html
grouper/fe/templates/users.html
grouper/fe/templates/email/pending_request_html.tmpl
grouper/fe/templates/email/pending_request_text.tmpl
grouper/fe/templates/errors/badrequest.html
grouper/fe/templates/errors/forbidden.html
grouper/fe/templates/errors/notfound.html
grouper/fe/templates/forms/group-join.html
grouper/fe/templates/forms/group-request-update.html
grouper/fe/templates/forms/group.html
grouper/fe/templates/macros/ui.html