Metadata-Version: 1.1
Name: grouper
Version: 0.0.1
Summary: Self-service Nested Group Management Server.
Home-page: https://github.com/dropbox/grouper
Author: Gary M. Josack
Author-email: gary@dropbox.com
License: Apache
Download-URL: https://github.com/dropbox/grouper/archive/master.tar.gz
Platform: UNKNOWN
Classifier: Programming Language :: Python
Classifier: Topic :: Software Development
Classifier: Topic :: Software Development :: Libraries
Classifier: Topic :: Software Development :: Libraries :: Python Modules
